Workbook

Sheet Sheet1
A1: 年月 | B1: 账户总额 | C1: 造音师 | D1: 期初金额 | E1: 净现金流 | F1: 期末余额 | G1: 经营净收益 | H1: 收款合计 | I1: 投资合计 | J1: 债务合计 | K1: 支出合计 | V1: 收入 | Y1: 风险金 | Z1: 副投 | AA1: 原生家庭 | AF1: 恋爱 | AG1: 基本生活 | AO1: 提升情绪 | AS1: 投资自己 | AW1: 健康基金 | BA1: 社保 | BH1: 投资 | BJ1: 借款还款 | BN1: 取得借款
K2: 总支 | L2: 风险金 | M2: 副投 | N2: 原生家庭 | O2: 恋爱 | P2: 基础 | Q2: 情绪 | R2: 投己 | S2: 健康 | T2: 社保 | U2: 不含恋爱、孝敬和风险金 | V2: 工资 | W2: 副入 | X2: 投资收益 | AA2: 孝敬 | AB2: 保山 | AC2: 养育 | AD2: 家医 | AE2: 小计 | AG2: 吃喝 | AH2: 房租 | AI2: 水电 | AJ2: 日用 | AK2: 住宿 | AL2: 出行 | AM2: 话费 | AN2: 小计 | AO2: 社交 | AP2: 小资 | AQ2: 游戏 | AR2: 小计 | AS2: 会员 | AT2: 读书 | AU2: 课程 | AV2: 小计 | AW2: 自医 | AX2: 运动 | AY2: 健它 | AZ2: 小计 | BA2: 医保 | BB2: 养老 | BC2: 生育 | BD2: 失业 | BE2: 商业 | BF2: 社杂 | BG2: 小计 | BH2: 对外投资 | BI2: 收回投资 | BJ2: 个人还本 | BK2: 网贷还本 | BL2: 还息 | BM2: 网诉 | BN2: 个人借款 | BO2: 网贷
A3: 202601 | B3: =C3+D3 -> 24361.43 | C3: 157.14 | D3: =[1]汇总!B33 -> 24204.29 | E3: =H3+I3+J3-K3 -> 28738.3 | F3: =D3+E3 -> 52942.59 | G3: =H3-K3 -> 25838.3 | H3: =SUM(V3:X3) -> 44000 | I3: =SUM(BH3:BI3) -> 3000 | J3: =SUM(BN3:BO3)-SUM(BJ3:BM3) -> -100 | K3: =SUM(Y3,Z3,AE3,AF3,AN3,AR3,AV3,BG3,AZ3) -> 18161.7 | L3: =Y3 -> 10000 | M3: =Z3 -> 0 | N3: =AE3 -> 4297 | O3: =AF3 -> 0 | P3: =AN3 -> 1062.91 | Q3: =AR3 -> 2589.49 | R3: =AV3 -> 212.3 | S3: =AZ3 -> 0 | T3: =BG3 -> 0 | U3: =SUM(P3:T3) -> 3864.7 | V3: =[1]汇总!K33 -> 44000 | W3: =[1]汇总!L33 -> 0 | X3: =[1]汇总!M33 -> 0 | Y3: =[1]汇总!X33 -> 10000 | Z3: =[1]汇总!Y33 -> 0 | AA3: =[1]汇总!Z33 -> 2000 | AB3: =[1]汇总!AA33 -> 0 | AC3: =[1]汇总!AB33 -> 2297 | AD3: =[1]汇总!AC33 -> 0 | AE3: =SUM(AA3:AD3) -> 4297 | AF3: =[1]汇总!AE33 -> 0 | AG3: =[1]汇总!AL33 -> 140 | AH3: =[1]汇总!AM33 -> 430 | AI3: =[1]汇总!AN33+[1]汇总!AO33 -> 9 | AJ3: =[1]汇总!AP33 -> 266.91 | AK3: =[1]汇总!AQ33 -> 0 | AL3: =[1]汇总!AR33 -> 27 | AM3: =[1]汇总!AS33 -> 190 | AN3: =SUM(AG3:AM3) -> 1062.91 | AO3: =[1]汇总!AU33 -> -37.84 | AP3: =[1]汇总!AV33 -> 2627.33 | AQ3: =[1]汇总!AW33 -> 0 | AR3: =SUM(AO3:AQ3) -> 2589.49 | AS3: =[1]汇总!AY33 -> 33 | AT3: =[1]汇总!AZ33 -> 106.9 | AU3: =[1]汇总!BA33 -> 72.4 | AV3: =SUM(AS3:AU3) -> 212.3 | AW3: =[1]汇总!BC33 -> 0 | AX3: =[1]汇总!BD33 -> 0 | AY3: =[1]汇总!BE33 -> 0 | AZ3: =SUM(AW3:AY3) -> 0 | BA3: =[1]汇总!BG33 -> 0 | BB3: =[1]汇总!BH33 -> 0 | BC3: =[1]汇总!BI33 -> 0 | BD3: =[1]汇总!BJ33 -> 0 | BE3: =[1]汇总!BK33 -> 0 | BF3: =[1]汇总!BL33 -> 0 | BG3: =[1]汇总!BM33 -> 0 | BH3: =[1]汇总!N33+[1]汇总!O33 -> 0 | BI3: =([1]汇总!P33+[1]汇总!Q33) -> 3000 | BJ3: =[1]汇总!R33 -> 0 | BK3: =[1]汇总!S33 -> 0 | BL3: =[1]汇总!T33 -> 0 | BM3: =[1]汇总!U33 -> 100 | BN3: =[1]汇总!V33 -> 0 | BO3: =[1]汇总!W33 -> 0
A4: 202602 | B4: =56573.36+0.5 -> 56573.86 | C4: 3631.27 | D4: =B4-C4 -> 52942.59 | E4: =H4+I4+J4-K4 -> 7686.93 | F4: =D4+E4 -> 60629.52 | G4: =H4-K4 -> 7709.93 | H4: =SUM(V4:X4) -> 22000 | I4: =SUM(BH4:BI4) -> 0 | J4: =SUM(BN4:BO4)-SUM(BJ4:BM4) -> -23 | K4: =SUM(Y4,Z4,AE4,AF4,AN4,AR4,AV4,BG4,AZ4) -> 14290.07 | L4: =Y4 -> 930 | M4: =Z4 -> 0 | N4: =AE4 -> 10456.83 | O4: =AF4 -> 0 | P4: =AN4 -> 2663.14 | Q4: =AR4 -> 211.1 | R4: =AV4 -> 29 | S4: =AZ4 -> 0 | T4: =BG4 -> 0 | U4: =SUM(P4:T4) -> 2903.24 | V4: =[1]汇总!K34 -> 22000 | W4: =[1]汇总!L34 -> 0 | X4: =[1]汇总!M34 -> 0 | Y4: =[1]汇总!X34 -> 930 | Z4: =[1]汇总!Y34 -> 0 | AA4: =[1]汇总!Z34 -> 9200 | AB4: =[1]汇总!AA34 -> 1654.83 | AC4: =[1]汇总!AB34 -> -398 | AD4: =[1]汇总!AC34 -> 0 | AE4: =SUM(AA4:AD4) -> 10456.83 | AF4: =[1]汇总!AE34 -> 0 | AG4: =[1]汇总!AL34 -> 117 | AH4: =[1]汇总!AM34 -> 300 | AI4: =[1]汇总!AN34+[1]汇总!AO34 -> 0 | AJ4: =[1]汇总!AP34 -> 1247.65 | AK4: =[1]汇总!AQ34 -> 0 | AL4: =[1]汇总!AR34 -> 649.49 | AM4: =[1]汇总!AS34 -> 349 | AN4: =SUM(AG4:AM4) -> 2663.14 | AO4: =[1]汇总!AU34 -> 188 | AP4: =[1]汇总!AV34 -> 23.1 | AQ4: =[1]汇总!AW34 -> 0 | AR4: =SUM(AO4:AQ4) -> 211.1 | AS4: =[1]汇总!AY34 -> 29 | AT4: =[1]汇总!AZ34 -> 0 | AU4: =[1]汇总!BA34 -> 0 | AV4: =SUM(AS4:AU4) -> 29 | AW4: =[1]汇总!BC34 -> 0 | AX4: =[1]汇总!BD34 -> 0 | AY4: =[1]汇总!BE34 -> 0 | AZ4: =SUM(AW4:AY4) -> 0 | BA4: =[1]汇总!BG34 -> 0 | BB4: =[1]汇总!BH34 -> 0 | BC4: =[1]汇总!BI34 -> 0 | BD4: =[1]汇总!BJ34 -> 0 | BE4: =[1]汇总!BK34 -> 0 | BF4: =[1]汇总!BL34 -> 0 | BG4: =[1]汇总!BM34 -> 0 | BH4: =[1]汇总!N34+[1]汇总!O34 -> 0 | BI4: =([1]汇总!P34+[1]汇总!Q34) -> 0 | BJ4: =[1]汇总!R34 -> 0 | BK4: =[1]汇总!S34 -> 0 | BL4: =[1]汇总!T34 -> 0 | BM4: =[1]汇总!U34 -> 23 | BN4: =[1]汇总!V34 -> 0 | BO4: =[1]汇总!W34 -> 0
A5: 202603 | B5: =0.5+64003.47 -> 64003.97 | C5: 3374.45 | D5: =B5-C5 -> 60629.52 | E5: =H5+I5+J5-K5 -> -14389.33 | F5: =D5+E5 -> 46240.19 | G5: =H5-K5 -> -14389.33 | H5: =SUM(V5:X5) -> 22000 | I5: =SUM(BH5:BI5) -> 0 | J5: =SUM(BN5:BO5)-SUM(BJ5:BM5) -> 0 | K5: =SUM(Y5,Z5,AE5,AF5,AN5,AR5,AV5,BG5,AZ5) -> 36389.33 | L5: =Y5 -> 30000 | M5: =Z5 -> 0 | N5: =AE5 -> 647.8 | O5: =AF5 -> 0 | P5: =AN5 -> 1584.68 | Q5: =AR5 -> 2134.29 | R5: =AV5 -> 765.8 | S5: =AZ5 -> 0 | T5: =BG5 -> 1256.76 | U5: =SUM(P5:T5) -> 5741.53 | V5: =[1]汇总!K35 -> 22000 | W5: =[1]汇总!L35 -> 0 | X5: =[1]汇总!M35 -> 0 | Y5: =[1]汇总!X35 -> 30000 | Z5: =[1]汇总!Y35 -> 0 | AA5: =[1]汇总!Z35 -> 0 | AB5: =[1]汇总!AA35 -> -60.2 | AC5: =[1]汇总!AB35 -> 708 | AD5: =[1]汇总!AC35 -> 0 | AE5: =SUM(AA5:AD5) -> 647.8 | AF5: =[1]汇总!AE35 -> 0 | AG5: =[1]汇总!AL35 -> 216 | AH5: =[1]汇总!AM35 -> 150 | AI5: =[1]汇总!AN35+[1]汇总!AO35 -> 0 | AJ5: =[1]汇总!AP35 -> 963.08 | AK5: =[1]汇总!AQ35 -> 0 | AL5: =[1]汇总!AR35 -> 106.6 | AM5: =[1]汇总!AS35 -> 149 | AN5: =SUM(AG5:AM5) -> 1584.68 | AO5: =[1]汇总!AU35 -> 599 | AP5: =[1]汇总!AV35 -> 1535.29 | AQ5: =[1]汇总!AW35 -> 0 | AR5: =SUM(AO5:AQ5) -> 2134.29 | AS5: =[1]汇总!AY35 -> 29 | AT5: =[1]汇总!AZ35 -> 0 | AU5: =[1]汇总!BA35 -> 736.8 | AV5: =SUM(AS5:AU5) -> 765.8 | AW5: =[1]汇总!BC35 -> 0 | AX5: =[1]汇总!BD35 -> 0 | AY5: =[1]汇总!BE35 -> 0 | AZ5: =SUM(AW5:AY5) -> 0 | BA5: =[1]汇总!BG35 -> 1256.76 | BB5: =[1]汇总!BH35 -> 0 | BC5: =[1]汇总!BI35 -> 0 | BD5: =[1]汇总!BJ35 -> 0 | BE5: =[1]汇总!BK35 -> 0 | BF5: =[1]汇总!BL35 -> 0 | BG5: =[1]汇总!BM35 -> 1256.76 | BH5: =[1]汇总!N35+[1]汇总!O35 -> 0 | BI5: =([1]汇总!P35+[1]汇总!Q35) -> 0 | BJ5: =[1]汇总!R35 -> 0 | BK5: =[1]汇总!S35 -> 0 | BL5: =[1]汇总!T35 -> 0 | BM5: =[1]汇总!U35 -> 0 | BN5: =[1]汇总!V35 -> 0 | BO5: =[1]汇总!W35 -> 0
A6: 202604 | B6: =0.5+48883.65 -> 48884.15 | C6: 2643.96 | D6: =B6-C6 -> 46240.19 | E6: =H6+I6+J6-K6 -> 16081.38 | F6: =D6+E6 -> 62321.57 | G6: =H6-K6 -> 16081.38 | H6: =SUM(V6:X6) -> 22000 | I6: =SUM(BH6:BI6) -> 0 | J6: =SUM(BN6:BO6)-SUM(BJ6:BM6) -> 0 | K6: =SUM(Y6,Z6,AE6,AF6,AN6,AR6,AV6,BG6,AZ6) -> 5918.62 | L6: =Y6 -> 0 | M6: =Z6 -> 0 | N6: =AE6 -> 0 | O6: =AF6 -> 0 | P6: =AN6 -> 3406.42 | Q6: =AR6 -> 2152.2 | R6: =AV6 -> 360 | S6: =AZ6 -> 0 | T6: =BG6 -> 0 | U6: =SUM(P6:T6) -> 5918.62 | V6: =[1]汇总!K36 -> 22000 | W6: =[1]汇总!L36 -> 0 | X6: =[1]汇总!M36 -> 0 | Y6: =[1]汇总!X36 -> 0 | Z6: =[1]汇总!Y36 -> 0 | AA6: =[1]汇总!Z36 -> 0 | AB6: =[1]汇总!AA36 -> 0 | AC6: =[1]汇总!AB36 -> 0 | AD6: =[1]汇总!AC36 -> 0 | AE6: =SUM(AA6:AD6) -> 0 | AF6: =[1]汇总!AE36 -> 0 | AG6: =[1]汇总!AL36 -> 432.2 | AH6: =[1]汇总!AM36 -> 20 | AI6: =[1]汇总!AN36+[1]汇总!AO36 -> 0 | AJ6: =[1]汇总!AP36 -> 1678.32 | AK6: =[1]汇总!AQ36 -> 243 | AL6: =[1]汇总!AR36 -> 742.9 | AM6: =[1]汇总!AS36 -> 290 | AN6: =SUM(AG6:AM6) -> 3406.42 | AO6: =[1]汇总!AU36 -> 511.6 | AP6: =[1]汇总!AV36 -> 1640.6 | AQ6: =[1]汇总!AW36 -> 0 | AR6: =SUM(AO6:AQ6) -> 2152.2 | AS6: =[1]汇总!AY36 -> 21 | AT6: =[1]汇总!AZ36 -> 0 | AU6: =[1]汇总!BA36 -> 339 | AV6: =SUM(AS6:AU6) -> 360 | AW6: =[1]汇总!BC36 -> 0 | AX6: =[1]汇总!BD36 -> 0 | AY6: =[1]汇总!BE36 -> 0 | AZ6: =SUM(AW6:AY6) -> 0 | BA6: =[1]汇总!BG36 -> 0 | BB6: =[1]汇总!BH36 -> 0 | BC6: =[1]汇总!BI36 -> 0 | BD6: =[1]汇总!BJ36 -> 0 | BE6: =[1]汇总!BK36 -> 0 | BF6: =[1]汇总!BL36 -> 0 | BG6: =[1]汇总!BM36 -> 0 | BH6: =[1]汇总!N36+[1]汇总!O36 -> 0 | BI6: =([1]汇总!P36+[1]汇总!Q36) -> 0 | BJ6: =[1]汇总!R36 -> 0 | BK6: =[1]汇总!S36 -> 0 | BL6: =[1]汇总!T36 -> 0 | BM6: =[1]汇总!U36 -> 0 | BN6: =[1]汇总!V36 -> 0 | BO6: =[1]汇总!W36 -> 0
A7: 202605 | B7: =0.5+64393.61 -> 64394.11 | C7: 2072.54 | D7: =B7-C7 -> 62321.57 | E7: =H7+I7+J7-K7 -> 3691.58 | F7: =D7+E7 -> 66013.15 | G7: =H7-K7 -> 3854.58 | H7: =SUM(V7:X7) -> 21511 | I7: =SUM(BH7:BI7) -> 5000 | J7: =SUM(BN7:BO7)-SUM(BJ7:BM7) -> -5163 | K7: =SUM(Y7,Z7,AE7,AF7,AN7,AR7,AV7,BG7,AZ7) -> 17656.42 | L7: =Y7 -> 0 | M7: =Z7 -> 1048.85 | N7: =AE7 -> 10237.8 | O7: =AF7 -> 0 | P7: =AN7 -> 4759.04 | Q7: =AR7 -> 949.61 | R7: =AV7 -> 29 | S7: =AZ7 -> 252.74 | T7: =BG7 -> 379.38 | U7: =SUM(P7:T7) -> 6369.77 | V7: =[1]汇总!K37 -> 0 | W7: =[1]汇总!L37 -> 21511 | X7: =[1]汇总!M37 -> 0 | Y7: =[1]汇总!X37 -> 0 | Z7: =[1]汇总!Y37 -> 1048.85 | AA7: =[1]汇总!Z37 -> 10000 | AB7: =[1]汇总!AA37 -> 0 | AC7: =[1]汇总!AB37 -> 109.8 | AD7: =[1]汇总!AC37 -> 128 | AE7: =SUM(AA7:AD7) -> 10237.8 | AF7: =[1]汇总!AE37 -> 0 | AG7: =[1]汇总!AL37 -> 1114.29 | AH7: =[1]汇总!AM37 -> 2800 | AI7: =[1]汇总!AN37+[1]汇总!AO37 -> 0 | AJ7: =[1]汇总!AP37 -> 185.27 | AK7: =[1]汇总!AQ37 -> 71.8 | AL7: =[1]汇总!AR37 -> 387.68 | AM7: =[1]汇总!AS37 -> 200 | AN7: =SUM(AG7:AM7) -> 4759.04 | AO7: =[1]汇总!AU37 -> 95 | AP7: =[1]汇总!AV37 -> 854.61 | AQ7: =[1]汇总!AW37 -> 0 | AR7: =SUM(AO7:AQ7) -> 949.61 | AS7: =[1]汇总!AY37 -> 29 | AT7: =[1]汇总!AZ37 -> 0 | AU7: =[1]汇总!BA37 -> 0 | AV7: =SUM(AS7:AU7) -> 29 | AW7: =[1]汇总!BC37 -> 252.74 | AX7: =[1]汇总!BD37 -> 0 | AY7: =[1]汇总!BE37 -> 0 | AZ7: =SUM(AW7:AY7) -> 252.74 | BA7: =[1]汇总!BG37 -> 379.38 | BB7: =[1]汇总!BH37 -> 0 | BC7: =[1]汇总!BI37 -> 0 | BD7: =[1]汇总!BJ37 -> 0 | BE7: =[1]汇总!BK37 -> 0 | BF7: =[1]汇总!BL37 -> 0 | BG7: =[1]汇总!BM37 -> 379.38 | BH7: =[1]汇总!N37+[1]汇总!O37 -> 0 | BI7: =([1]汇总!P37+[1]汇总!Q37) -> 5000 | BJ7: =[1]汇总!R37 -> 0 | BK7: =[1]汇总!S37 -> 5163 | BL7: =[1]汇总!T37 -> 0 | BM7: =[1]汇总!U37 -> 0 | BN7: =[1]汇总!V37 -> 0 | BO7: =[1]汇总!W37 -> 0
A8: 202606 | B8: =2858.5+222+5.19+65000 -> 68085.69 | C8: 2072.54 | D8: =B8-C8 -> 66013.15 | E8: =H8+I8+J8-K8 -> -9479.86 | F8: =D8+E8 -> 56533.29 | G8: =H8-K8 -> -8677.86 | H8: =SUM(V8:X8) -> 122 | I8: =SUM(BH8:BI8) -> 0 | J8: =SUM(BN8:BO8)-SUM(BJ8:BM8) -> -802 | K8: =SUM(Y8,Z8,AE8,AF8,AN8,AR8,AV8,BG8,AZ8) -> 8799.86 | L8: =Y8 -> 300 | M8: =Z8 -> 777.46 | N8: =AE8 -> 2000 | O8: =AF8 -> 0 | P8: =AN8 -> 3167.96 | Q8: =AR8 -> 1689.9 | R8: =AV8 -> 1117.28 | S8: =AZ8 -> -252.74 | T8: =BG8 -> 0 | U8: =SUM(P8:T8) -> 5722.4 | V8: =[1]汇总!K38 -> 0 | W8: =[1]汇总!L38 -> 122 | X8: =[1]汇总!M38 -> 0 | Y8: =[1]汇总!X38 -> 300 | Z8: =[1]汇总!Y38 -> 777.46 | AA8: =[1]汇总!Z38 -> 2000 | AB8: =[1]汇总!AA38 -> 0 | AC8: =[1]汇总!AB38 -> 0 | AD8: =[1]汇总!AC38 -> 0 | AE8: =SUM(AA8:AD8) -> 2000 | AF8: =[1]汇总!AE38 -> 0 | AG8: =[1]汇总!AL38 -> 959.21 | AH8: =[1]汇总!AM38 -> 1320 | AI8: =[1]汇总!AN38+[1]汇总!AO38 -> 0 | AJ8: =[1]汇总!AP38 -> 592.15 | AK8: =[1]汇总!AQ38 -> 0 | AL8: =[1]汇总!AR38 -> 106.6 | AM8: =[1]汇总!AS38 -> 190 | AN8: =SUM(AG8:AM8) -> 3167.96 | AO8: =[1]汇总!AU38 -> 552.8 | AP8: =[1]汇总!AV38 -> 1137.1 | AQ8: =[1]汇总!AW38 -> 0 | AR8: =SUM(AO8:AQ8) -> 1689.9 | AS8: =[1]汇总!AY38 -> 332.69 | AT8: =[1]汇总!AZ38 -> 0 | AU8: =[1]汇总!BA38 -> 784.59 | AV8: =SUM(AS8:AU8) -> 1117.28 | AW8: =[1]汇总!BC38 -> -252.74 | AX8: =[1]汇总!BD38 -> 0 | AY8: =[1]汇总!BE38 -> 0 | AZ8: =SUM(AW8:AY8) -> -252.74 | BA8: =[1]汇总!BG38 -> 0 | BB8: =[1]汇总!BH38 -> 0 | BC8: =[1]汇总!BI38 -> 0 | BD8: =[1]汇总!BJ38 -> 0 | BE8: =[1]汇总!BK38 -> 0 | BF8: =[1]汇总!BL38 -> 0 | BG8: =[1]汇总!BM38 -> 0 | BH8: =[1]汇总!N38+[1]汇总!O38 -> 0 | BI8: =([1]汇总!P38+[1]汇总!Q38) -> 0 | BJ8: =[1]汇总!R38 -> 0 | BK8: =[1]汇总!S38 -> 802 | BL8: =[1]汇总!T38 -> 0 | BM8: =[1]汇总!U38 -> 0 | BN8: =[1]汇总!V38 -> 0 | BO8: =[1]汇总!W38 -> 0
A9: 202607 | B9: =2580.89+0.19+55000 -> 57581.08 | C9: 1047.79 | D9: =B9-C9 -> 56533.29 | E9: =H9+I9+J9-K9 -> -2.05 | F9: =D9+E9 -> 56531.24 | G9: =H9-K9 -> -2.05 | H9: =SUM(V9:X9) -> 0 | I9: =SUM(BH9:BI9) -> 0 | J9: =SUM(BN9:BO9)-SUM(BJ9:BM9) -> 0 | K9: =SUM(Y9,Z9,AE9,AF9,AN9,AR9,AV9,BG9,AZ9) -> 2.05 | L9: =Y9 -> 0 | M9: =Z9 -> 0 | N9: =AE9 -> 0 | O9: =AF9 -> 0 | P9: =AN9 -> 2.05 | Q9: =AR9 -> 0 | R9: =AV9 -> 0 | S9: =AZ9 -> 0 | T9: =BG9 -> 0 | U9: =SUM(P9:T9) -> 2.05 | V9: =[1]汇总!K39 -> 0 | W9: =[1]汇总!L39 -> 0 | X9: =[1]汇总!M39 -> 0 | Y9: =[1]汇总!X39 -> 0 | Z9: =[1]汇总!Y39 -> 0 | AA9: =[1]汇总!Z39 -> 0 | AB9: =[1]汇总!AA39 -> 0 | AC9: =[1]汇总!AB39 -> 0 | AD9: =[1]汇总!AC39 -> 0 | AE9: =SUM(AA9:AD9) -> 0 | AF9: =[1]汇总!AE39 -> 0 | AG9: =[1]汇总!AL39 -> 0 | AH9: =[1]汇总!AM39 -> 0 | AI9: =[1]汇总!AN39+[1]汇总!AO39 -> 0 | AJ9: =[1]汇总!AP39 -> 2.05 | AK9: =[1]汇总!AQ39 -> 0 | AL9: =[1]汇总!AR39 -> 0 | AM9: =[1]汇总!AS39 -> 0 | AN9: =SUM(AG9:AM9) -> 2.05 | AO9: =[1]汇总!AU39 -> 0 | AP9: =[1]汇总!AV39 -> 0 | AQ9: =[1]汇总!AW39 -> 0 | AR9: =SUM(AO9:AQ9) -> 0 | AS9: =[1]汇总!AY39 -> 0 | AT9: =[1]汇总!AZ39 -> 0 | AU9: =[1]汇总!BA39 -> 0 | AV9: =SUM(AS9:AU9) -> 0 | AW9: =[1]汇总!BC39 -> 0 | AX9: =[1]汇总!BD39 -> 0 | AY9: =[1]汇总!BE39 -> 0 | AZ9: =SUM(AW9:AY9) -> 0 | BA9: =[1]汇总!BG39 -> 0 | BB9: =[1]汇总!BH39 -> 0 | BC9: =[1]汇总!BI39 -> 0 | BD9: =[1]汇总!BJ39 -> 0 | BE9: =[1]汇总!BK39 -> 0 | BF9: =[1]汇总!BL39 -> 0 | BG9: =[1]汇总!BM39 -> 0 | BH9: =[1]汇总!N39+[1]汇总!O39 -> 0 | BI9: =([1]汇总!P39+[1]汇总!Q39) -> 0 | BJ9: =[1]汇总!R39 -> 0 | BK9: =[1]汇总!S39 -> 0 | BL9: =[1]汇总!T39 -> 0 | BM9: =[1]汇总!U39 -> 0 | BN9: =[1]汇总!V39 -> 0 | BO9: =[1]汇总!W39 -> 0
A10: 202608 | B10: =2578.84+0.19+55000 -> 57579.03 | C10: 1047.79 | D10: =B10-C10 -> 56531.24 | E10: =H10+I10+J10-K10 -> 0 | K10: =SUM(Y10,Z10,AE10,AF10,AN10,AR10,AV10,BG10,AZ10) -> 0 | L10: =Y10 -> 0 | M10: =Z10 -> 0 | N10: =AE10 -> 0 | O10: =AF10 -> 0 | P10: =AN10 -> 0 | Q10: =AR10 -> 0 | R10: =AV10 -> 0 | S10: =AZ10 -> 0 | T10: =BG10 -> 0 | U10: =SUM(P10:T10) -> 0 | BG10: =SUM(BA10:BF10) -> 0
A11: 202609 | E11: =H11+I11+J11-K11 -> 0 | K11: =SUM(Y11,Z11,AE11,AF11,AN11,AR11,AV11,BG11,AZ11) -> 0 | L11: =Y11 -> 0 | M11: =Z11 -> 0 | N11: =AE11 -> 0 | O11: =AF11 -> 0 | P11: =AN11 -> 0 | Q11: =AR11 -> 0 | R11: =AV11 -> 0 | S11: =AZ11 -> 0 | T11: =BG11 -> 0 | U11: =SUM(P11:T11) -> 0 | BG11: =SUM(BA11:BF11) -> 0
A12: 202610 | E12: =H12+I12+J12-K12 -> 0 | K12: =SUM(Y12,Z12,AE12,AF12,AN12,AR12,AV12,BG12,AZ12) -> 0 | L12: =Y12 -> 0 | M12: =Z12 -> 0 | N12: =AE12 -> 0 | O12: =AF12 -> 0 | P12: =AN12 -> 0 | Q12: =AR12 -> 0 | R12: =AV12 -> 0 | S12: =AZ12 -> 0 | T12: =BG12 -> 0 | U12: =SUM(P12:T12) -> 0 | BG12: =SUM(BA12:BF12) -> 0
A13: 202611 | E13: =H13+I13+J13-K13 -> 0 | K13: =SUM(Y13,Z13,AE13,AF13,AN13,AR13,AV13,BG13,AZ13) -> 0 | L13: =Y13 -> 0 | M13: =Z13 -> 0 | N13: =AE13 -> 0 | O13: =AF13 -> 0 | P13: =AN13 -> 0 | Q13: =AR13 -> 0 | R13: =AV13 -> 0 | S13: =AZ13 -> 0 | T13: =BG13 -> 0 | U13: =SUM(P13:T13) -> 0 | BG13: =SUM(BA13:BF13) -> 0
A14: 202612 | E14: =H14+I14+J14-K14 -> 0 | K14: =SUM(Y14,Z14,AE14,AF14,AN14,AR14,AV14,BG14,AZ14) -> 0 | L14: =Y14 -> 0 | M14: =Z14 -> 0 | N14: =AE14 -> 0 | O14: =AF14 -> 0 | P14: =AN14 -> 0 | Q14: =AR14 -> 0 | R14: =AV14 -> 0 | S14: =AZ14 -> 0 | T14: =BG14 -> 0 | U14: =SUM(P14:T14) -> 0 | BG14: =SUM(BA14:BF14) -> 0
A15: 合计 | E15: =SUM(E3:E14) -> 32326.95 | G15: =SUM(G3:G14) -> 30414.95 | H15: =SUM(H3:H14) -> 131633 | I15: =SUM(I3:I14) -> 8000 | J15: =SUM(J3:J14) -> -6088 | K15: =SUM(Y15,Z15,AE15,AF15,AN15,AR15,AV15,BG15,AZ15) -> 101218.05 | L15: =SUM(L3:L14) -> 41230 | M15: =SUM(M3:M14) -> 1826.31 | N15: =SUM(N3:N14) -> 27639.43 | O15: =SUM(O3:O14) -> 0 | P15: =SUM(P3:P14) -> 16646.2 | Q15: =SUM(Q3:Q14) -> 9726.59 | R15: =SUM(R3:R14) -> 2513.38 | S15: =SUM(S3:S14) -> 0 | ... BO15: =SUM(BO3:BO14) -> 0
D16: 验证首尾 | E16: {=LOOKUP(2,1/(F3:F14<>""),F3:F14)-LOOKUP(2,1/(D3:D14<>""),D3:D14)} -> 0 | J16: 验证明细 | K16: =SUM(L15:T15)-K15+U15-SUM(P15:T15) -> 0 | U16: =SUM(P15:T15)-U15 -> 0
