Workbook

Sheet 原料采购价格表
A1: 织造部原料采购价格表
A2: 说明：黄色单元格为输入区，请填入实际采购价格
A4: 序号 | B4: 原料类别 | C4: 纱支规格 | D4: 采购单价(元/kg) | E4: 供应商 | F4: 备注
A5: 1 | B5: 棉纱 | C5: 20S | E5: 待填 | F5: 粗支纱
A6: 2 | B6: 棉纱 | C6: 30S | E6: 待填 | F6: 常规T恤用纱
A7: 3 | B7: 棉纱 | C7: 40S | E7: 待填 | F7: 高档面料用纱
A8: 4 | B8: 涤纶 | C8: 75D/36F | E8: 待填 | F8: 标准涤纶丝
A9: 5 | B9: 涤纶 | C9: 75D/72F | E9: 待填 | F9: 细旦涤纶,手感好
A10: 6 | B10: 氨纶 | C10: 20D | E10: 待填 | F10: 轻薄面料用
A11: 7 | B11: 氨纶 | C11: 30D | E11: 待填 | F11: 常规弹力面料
A12: 8 | B12: 氨纶 | C12: 40D | E12: 待填 | F12: 运动/瑜伽面料

Sheet 品种BOM与标准成本
A1: 品种BOM与标准成本卡
A2: 说明：黄色=手工输入，绿色=自动计算。成布率=成品入库kg÷领料kg
A4: 品种编码 | B4: 品种名称 | C4: 纱支信息 | D4: 原料1-纱支 | E4: 配比% | F4: 单价 | G4: 投入kg | H4: 金额 | I4: 原料2-纱支 | J4: 配比% | K4: 单价 | L4: 投入kg
A5: P001 | B5: 40S/1棉+30D氨纶平纹布 | C5: 40S棉+30D | D5: 40S棉纱 | E5: 94.2 | F5: =VLOOKUP(D5,原料采购价格表!$C$5:$D$20,2,0) -> #N/A | G5: =(1/N5)*(E5/100) -> 0.01023913 | H5: =F5*G5 -> #N/A | I5: 30D氨纶 | J5: 5.8 | K5: =VLOOKUP(I5,原料采购价格表!$C$5:$D$20,2,0) -> #N/A | L5: =(1/N5)*(J5/100) -> 0.00063043478 | M5: =K5*L5 -> #N/A | N5: 92 | O5: =H5+M5 -> #N/A | P5: 8.5 | Q5: =O5+P5 -> #N/A | R5: 20 | S5: =Q5/(1-R5/100) -> #N/A
F6: =VLOOKUP(D6,原料采购价格表!$C$5:$D$20,2,0) -> #N/A | G6: =(1/N6)*(E6/100) -> #DIV/0! | H6: =F6*G6 -> #N/A | K6: =VLOOKUP(I6,原料采购价格表!$C$5:$D$20,2,0) -> #N/A | L6: =(1/N6)*(J6/100) -> #DIV/0! | M6: =K6*L6 -> #N/A | O6: =H6+M6 -> #N/A | Q6: =O6+P6 -> #N/A | S6: =Q6/(1-R6/100) -> #N/A

Sheet 订单实际成本归集
A1: 订单实际成本归集表（月度）
A2: 说明：黄色=实际数据录入，绿色=自动计算。用于月底倒算实际成本
A4: 订单号 | B4: 品种编码 | C4: 品种名称 | D4: 计划产量kg | E4: 实际入库kg | F4: 实际领料kg | G4: 标准成本/kg | H4: 实际材料成本 | I4: 实际人工成本 | J4: 实际制造费用 | K4: 实际总成本 | L4: 实际单位成本/kg | M4: 报价单价/kg | N4: 实际毛利率% | O4: 差异分析
A5: S260813005 | B5: P001 | C5: 40S/1棉+30D氨纶 | D5: 80 | E5: 78.5 | F5: 85.2 | G5: =VLOOKUP(B5,品种BOM与标准成本!$A$5:$Q$20,17,0) -> #N/A | H5: =F5*VLOOKUP(B5,品种BOM与标准成本!$A$5:$O$20,15,0) -> #N/A | I5: 520 | J5: 180 | K5: =H5+I5+J5 -> #N/A | L5: =K5/E5 -> #N/A | M5: 52 | N5: =(M5-L5)/M5*100 -> #N/A | O5: =IF(L5>G5,"超支","达标") -> #N/A
G6: =VLOOKUP(B6,品种BOM与标准成本!$A$5:$Q$20,17,0) -> #N/A | H6: =F6*VLOOKUP(B6,品种BOM与标准成本!$A$5:$O$20,15,0) -> #N/A | K6: =H6+I6+J6 -> #N/A | L6: =K6/E6 -> #N/A | N6: =(M6-L6)/M6*100 -> #N/A | O6: =IF(L6>G6,"超支","达标") -> #N/A
G7: =VLOOKUP(B7,品种BOM与标准成本!$A$5:$Q$20,17,0) -> #N/A | H7: =F7*VLOOKUP(B7,品种BOM与标准成本!$A$5:$O$20,15,0) -> #N/A | K7: =H7+I7+J7 -> #N/A | L7: =K7/E7 -> #N/A | N7: =(M7-L7)/M7*100 -> #N/A | O7: =IF(L7>G7,"超支","达标") -> #N/A
G8: =VLOOKUP(B8,品种BOM与标准成本!$A$5:$Q$20,17,0) -> #N/A | H8: =F8*VLOOKUP(B8,品种BOM与标准成本!$A$5:$O$20,15,0) -> #N/A | K8: =H8+I8+J8 -> #N/A | L8: =K8/E8 -> #N/A | N8: =(M8-L8)/M8*100 -> #N/A | O8: =IF(L8>G8,"超支","达标") -> #N/A
G9: =VLOOKUP(B9,品种BOM与标准成本!$A$5:$Q$20,17,0) -> #N/A | H9: =F9*VLOOKUP(B9,品种BOM与标准成本!$A$5:$O$20,15,0) -> #N/A | K9: =H9+I9+J9 -> #N/A | L9: =K9/E9 -> #N/A | N9: =(M9-L9)/M9*100 -> #N/A | O9: =IF(L9>G9,"超支","达标") -> #N/A
G10: =VLOOKUP(B10,品种BOM与标准成本!$A$5:$Q$20,17,0) -> #N/A | H10: =F10*VLOOKUP(B10,品种BOM与标准成本!$A$5:$O$20,15,0) -> #N/A | K10: =H10+I10+J10 -> #N/A | L10: =K10/E10 -> #N/A | N10: =(M10-L10)/M10*100 -> #N/A | O10: =IF(L10>G10,"超支","达标") -> #N/A

Sheet 月度成本差异分析
A1: 品种横向对比 - 成本差异分析
A2: 说明：自动从订单表汇总，横向对比各品种的盈利能力
A4: 品种编码 | B4: 品种名称 | C4: 订单数量 | D4: 总产量kg | E4: 标准成本/kg | F4: 实际成本/kg | G4: 成本差异 | H4: 平均报价/kg | I4: 标准毛利率% | J4: 实际毛利率% | K4: 评价
A5: P001 | B5: 40S/1棉+30D氨纶 | C5: =COUNTIF(订单实际成本归集!$B$5:$B$50,A5) -> 1 | D5: =SUMIF(订单实际成本归集!$B$5:$B$50,A5,订单实际成本归集!$E$5:$E$50) -> 78.5 | E5: =VLOOKUP(A5,品种BOM与标准成本!$A$5:$Q$20,17,0) -> #N/A | F5: =SUMIF(订单实际成本归集!$B$5:$B$50,A5,订单实际成本归集!$K$5:$K$50)/D5 -> #N/A | G5: =F5-E5 -> #N/A | H5: =SUMIF(订单实际成本归集!$B$5:$B$50,A5,订单实际成本归集!$M$5:$M$50)/C5 -> 52 | I5: =(H5-E5)/H5*100 -> #N/A | J5: =(H5-F5)/H5*100 -> #N/A | K5: =IF(J5<15,"亏损",IF(J5<20,"低利","正常")) -> #N/A
C6: =COUNTIF(订单实际成本归集!$B$5:$B$50,A6) -> 0 | D6: =SUMIF(订单实际成本归集!$B$5:$B$50,A6,订单实际成本归集!$E$5:$E$50) -> 0 | E6: =VLOOKUP(A6,品种BOM与标准成本!$A$5:$Q$20,17,0) -> #N/A | F6: =SUMIF(订单实际成本归集!$B$5:$B$50,A6,订单实际成本归集!$K$5:$K$50)/D6 -> #DIV/0! | G6: =F6-E6 -> #DIV/0! | H6: =SUMIF(订单实际成本归集!$B$5:$B$50,A6,订单实际成本归集!$M$5:$M$50)/C6 -> #DIV/0! | I6: =(H6-E6)/H6*100 -> #DIV/0! | J6: =(H6-F6)/H6*100 -> #DIV/0! | K6: =IF(J6<15,"亏损",IF(J6<20,"低利","正常")) -> #DIV/0!
C7: =COUNTIF(订单实际成本归集!$B$5:$B$50,A7) -> 0 | D7: =SUMIF(订单实际成本归集!$B$5:$B$50,A7,订单实际成本归集!$E$5:$E$50) -> 0 | E7: =VLOOKUP(A7,品种BOM与标准成本!$A$5:$Q$20,17,0) -> #N/A | F7: =SUMIF(订单实际成本归集!$B$5:$B$50,A7,订单实际成本归集!$K$5:$K$50)/D7 -> #DIV/0! | G7: =F7-E7 -> #DIV/0! | H7: =SUMIF(订单实际成本归集!$B$5:$B$50,A7,订单实际成本归集!$M$5:$M$50)/C7 -> #DIV/0! | I7: =(H7-E7)/H7*100 -> #DIV/0! | J7: =(H7-F7)/H7*100 -> #DIV/0! | K7: =IF(J7<15,"亏损",IF(J7<20,"低利","正常")) -> #DIV/0!
C8: =COUNTIF(订单实际成本归集!$B$5:$B$50,A8) -> 0 | D8: =SUMIF(订单实际成本归集!$B$5:$B$50,A8,订单实际成本归集!$E$5:$E$50) -> 0 | E8: =VLOOKUP(A8,品种BOM与标准成本!$A$5:$Q$20,17,0) -> #N/A | F8: =SUMIF(订单实际成本归集!$B$5:$B$50,A8,订单实际成本归集!$K$5:$K$50)/D8 -> #DIV/0! | G8: =F8-E8 -> #DIV/0! | H8: =SUMIF(订单实际成本归集!$B$5:$B$50,A8,订单实际成本归集!$M$5:$M$50)/C8 -> #DIV/0! | I8: =(H8-E8)/H8*100 -> #DIV/0! | J8: =(H8-F8)/H8*100 -> #DIV/0! | K8: =IF(J8<15,"亏损",IF(J8<20,"低利","正常")) -> #DIV/0!
C9: =COUNTIF(订单实际成本归集!$B$5:$B$50,A9) -> 0 | D9: =SUMIF(订单实际成本归集!$B$5:$B$50,A9,订单实际成本归集!$E$5:$E$50) -> 0 | E9: =VLOOKUP(A9,品种BOM与标准成本!$A$5:$Q$20,17,0) -> #N/A | F9: =SUMIF(订单实际成本归集!$B$5:$B$50,A9,订单实际成本归集!$K$5:$K$50)/D9 -> #DIV/0! | G9: =F9-E9 -> #DIV/0! | H9: =SUMIF(订单实际成本归集!$B$5:$B$50,A9,订单实际成本归集!$M$5:$M$50)/C9 -> #DIV/0! | I9: =(H9-E9)/H9*100 -> #DIV/0! | J9: =(H9-F9)/H9*100 -> #DIV/0! | K9: =IF(J9<15,"亏损",IF(J9<20,"低利","正常")) -> #DIV/0!
C10: =COUNTIF(订单实际成本归集!$B$5:$B$50,A10) -> 0 | D10: =SUMIF(订单实际成本归集!$B$5:$B$50,A10,订单实际成本归集!$E$5:$E$50) -> 0 | E10: =VLOOKUP(A10,品种BOM与标准成本!$A$5:$Q$20,17,0) -> #N/A | F10: =SUMIF(订单实际成本归集!$B$5:$B$50,A10,订单实际成本归集!$K$5:$K$50)/D10 -> #DIV/0! | G10: =F10-E10 -> #DIV/0! | H10: =SUMIF(订单实际成本归集!$B$5:$B$50,A10,订单实际成本归集!$M$5:$M$50)/C10 -> #DIV/0! | I10: =(H10-E10)/H10*100 -> #DIV/0! | J10: =(H10-F10)/H10*100 -> #DIV/0! | K10: =IF(J10<15,"亏损",IF(J10<20,"低利","正常")) -> #DIV/0!
